termtap/__init__.py
termtap/__main__.py
termtap/app.py
termtap/pane.py
termtap/paths.py
termtap/types.py
termtap/client/__init__.py
termtap/client/rpc.py
termtap/commands/__init__.py
termtap/commands/_helpers.py
termtap/commands/debug.py
termtap/commands/execute.py
termtap/commands/interrupt.py
termtap/commands/ls.py
termtap/commands/pane.py
termtap/commands/send_keystrokes.py
termtap/daemon/__init__.py
termtap/daemon/collector.py
termtap/daemon/context.py
termtap/daemon/lifecycle.py
termtap/daemon/queue.py
termtap/daemon/rpc.py
termtap/daemon/server.py
termtap/daemon/handlers/__init__.py
termtap/daemon/handlers/actions.py
termtap/daemon/handlers/commands.py
termtap/daemon/handlers/diagnostics.py
termtap/daemon/handlers/helpers.py
termtap/daemon/handlers/panes.py
termtap/daemon/handlers/patterns.py
termtap/handler/__init__.py
termtap/handler/hooks.py
termtap/handler/patterns.py
termtap/terminal/__init__.py
termtap/terminal/line_buffer.py
termtap/terminal/manager.py
termtap/terminal/pane_terminal.py
termtap/terminal/slim_screen.py
termtap/tmux/__init__.py
termtap/tmux/_exceptions.py
termtap/tmux/_structure.py
termtap/tmux/core.py
termtap/tmux/ops.py
termtap/tmux/resolution.py
termtap/ui/__init__.py
termtap/ui/companion.py
termtap/ui/companion.tcss
termtap/ui/popup.py
termtap/ui/tokens.py
termtap/ui/screens/__init__.py
termtap/ui/screens/_base.py
termtap/ui/screens/dsl_syntax_screen.py
termtap/ui/screens/pane_select_screen.py
termtap/ui/screens/pattern_editor_screen.py
termtap/ui/screens/pattern_list_screen.py
termtap/ui/screens/pattern_screen.py
termtap/ui/screens/queue_screen.py
termtap/ui/widgets/__init__.py
termtap/ui/widgets/background.py
termtap/ui/widgets/base.py
termtap/ui/widgets/cards.py
termtap/ui/widgets/dsl_reference.py
termtap/ui/widgets/fzf_selector.py
termtap/ui/widgets/logo_text.py
termtap/ui/widgets/output_pane.py
termtap/ui/widgets/pattern_editor.py
termtap/ui/widgets/preview_pane.py
termtap-0.13.1.dist-info/METADATA
termtap-0.13.1.dist-info/WHEEL
termtap-0.13.1.dist-info/entry_points.txt
termtap-0.13.1.dist-info/RECORD
