Metadata-Version: 2.4
Name: termtap
Version: 0.13.1
Summary: Daemon-based tmux pane manager with learning patterns
Project-URL: Repository, https://github.com/angelsen/tap-tools
Author-email: Fredrik Angelsen <fredrikangelsen@gmail.com>
License: MIT
Keywords: daemon,mcp,terminal,tmux
Classifier: Development Status :: 4 - Beta
Classifier: Operating System :: MacOS :: MacOS X
Classifier: Operating System :: POSIX :: Linux
Classifier: Programming Language :: Python :: 3.12
Classifier: Topic :: Software Development :: Libraries :: Python Modules
Classifier: Topic :: System :: Shells
Requires-Python: >=3.12
Requires-Dist: platformdirs>=4.4.0
Requires-Dist: pyte>=0.8.2
Requires-Dist: pyyaml>=6.0.2
Requires-Dist: replkit2[all]>=0.12.0
Requires-Dist: textual-coloromatic>=1.0.0
Requires-Dist: textual-pyfiglet>=1.0.0
Requires-Dist: textual>=7.0.3
Provides-Extra: examples
Requires-Dist: fastapi>=0.116.1; extra == 'examples'
Requires-Dist: uvicorn>=0.35.0; extra == 'examples'
